quark_plugin_myqlm/__init__.py
quark_plugin_myqlm/devices.py
quark_plugin_myqlm/mappings.py
quark_plugin_myqlm-0.0.1.dist-info/licenses/LICENSE
quark_plugin_myqlm-0.0.1.dist-info/licenses/NOTICE
quark_plugin_myqlm-0.0.1.dist-info/METADATA
quark_plugin_myqlm-0.0.1.dist-info/WHEEL
quark_plugin_myqlm-0.0.1.dist-info/top_level.txt
quark_plugin_myqlm-0.0.1.dist-info/RECORD
