Metadata-Version: 2.4
Name: QUARK-plugin-myqlm
Version: 0.0.1
License-Expression: Apache-2.0
Project-URL: Homepage, https://github.com/srmaschek/QUARK-plugin-myqlm
Classifier: Programming Language :: Python :: 3
Classifier: Operating System :: OS Independent
Requires-Python: >=3.12
License-File: LICENSE
License-File: NOTICE
Requires-Dist: quark-framework>=0.3.7
Requires-Dist: QUARK-plugin-ghz
Requires-Dist: myqlm>=1.11.3
Requires-Dist: myqlm-interop>=1.10.0
Dynamic: license-file
